paguro/__init__.py
paguro/_version.py
paguro/exceptions.py
paguro/typing.py
paguro/ashi/__init__.py
paguro/ashi/terminal.py
paguro/ashi/typing.py
paguro/ashi/info/__init__.py
paguro/ashi/info/info.py
paguro/ashi/info/info_collection.py
paguro/ashi/info/utils.py
paguro/ashi/repr/__init__.py
paguro/ashi/repr/utils.py
paguro/ashi/repr/html/__init__.py
paguro/ashi/repr/html/_html.py
paguro/ashi/repr/html/_html_dataset.py
paguro/ashi/repr/html/html_dict.py
paguro/ashi/repr/html/utility.py
paguro/ashi/repr/string/__init__.py
paguro/ashi/repr/string/dicts.py
paguro/ashi/repr/string/utils.py
paguro/ashi/repr/string/utils_tree.py
paguro/ashi/repr/string/box/__init__.py
paguro/ashi/repr/string/box/box.py
paguro/ashi/repr/string/box/templates.py
paguro/ashi/repr/string/box/utils.py
paguro/ashi/repr/string/frames/__init__.py
paguro/ashi/repr/string/frames/cast_to_string.py
paguro/ashi/repr/string/frames/frames.py
paguro/ashi/repr/string/frames/separators.py
paguro/ashi/repr/string/frames/titles.py
paguro/ashi/repr/string/styled/__init__.py
paguro/ashi/repr/string/styled/styled_dict.py
paguro/ashi/repr/string/styled/styled_str.py
paguro/ashi/utils/__init__.py
paguro/ashi/utils/terminal.py
paguro/collection/__init__.py
paguro/collection/_collection.py
paguro/collection/collection.py
paguro/collection/lazycollection.py
paguro/collection/io/__init__.py
paguro/collection/io/io.py
paguro/collection/io/utils.py
paguro/collection/utils/__init__.py
paguro/collection/utils/_group_by.py
paguro/dataset/__init__.py
paguro/dataset/_dataset.py
paguro/dataset/dataset.py
paguro/dataset/lazydataset.py
paguro/dataset/io/__init__.py
paguro/dataset/io/read_source.py
paguro/dataset/io/metadata/__init__.py
paguro/dataset/io/metadata/metadata.py
paguro/dataset/io/metadata/serialize.py
paguro/dataset/utils/__init__.py
paguro/dataset/utils/_get_renaming.py
paguro/dataset/utils/_group_by.py
paguro/dataset/utils/utils.py
paguro/defer/__init__.py
paguro/defer/_deferred.py
paguro/defer/frames.py
paguro-0.3.1.dist-info/licenses/LICENSE
paguro-0.3.1.dist-info/METADATA
paguro-0.3.1.dist-info/WHEEL
paguro-0.3.1.dist-info/top_level.txt
paguro-0.3.1.dist-info/RECORD
