Metadata-Version: 2.4
Name: paguro
Version: 0.3.1
Summary: Data validation and manipulation using Polars
Author-email: Bernardo Dionisi <bernardo.dionisi@gmail.com>
License: Apache-2.0
Project-URL: Homepage, https://github.com/bernardodionisi/paguro
Project-URL: Source, https://github.com/bernardodionisi/paguro
Project-URL: Issues, https://github.com/bernardodionisi/paguro/issues
Project-URL: Documentation, https://bernardodionisi.github.io/paguro/latest/
Keywords: data science,data quality,data engineering,polars,metadata,validation,summary statistics,deferred pipelines
Classifier: Topic :: Software Development :: Libraries :: Python Modules
Classifier: License :: OSI Approved :: Apache Software License
Classifier: Programming Language :: Python :: 3.10
Classifier: Programming Language :: Python :: 3.11
Classifier: Programming Language :: Python :: 3.12
Classifier: Programming Language :: Python :: 3.13
Classifier: Programming Language :: Python :: 3.14
Classifier: Operating System :: OS Independent
Requires-Python: >=3.10
License-File: LICENSE
Requires-Dist: polars>=1.32.0
Requires-Dist: typing_extensions>=4.0.0; python_version < "3.11"
Provides-Extra: extra
Requires-Dist: numpy>=1.23.0; extra == "extra"
Requires-Dist: rich; extra == "extra"
Provides-Extra: test
Requires-Dist: pytest; extra == "test"
Requires-Dist: pytest-cov; extra == "test"
Requires-Dist: pytest-xdist; extra == "test"
Requires-Dist: nox; extra == "test"
Provides-Extra: lint
Requires-Dist: ruff==0.9.2; extra == "lint"
Provides-Extra: typing
Requires-Dist: mypy; extra == "typing"
Provides-Extra: docs
Requires-Dist: sphinx-tutorials==0.0.7; extra == "docs"
Dynamic: license-file
